MANIFEST.in
README.md
VERSION
requirements-tests.txt
requirements.txt
setup.cfg
setup.py
menhir/__init__.py
menhir/config.py
menhir/fileutils.py
menhir/gitutils.py
menhir/graph.py
menhir/project.py
menhir/script.py
menhir/tool.py
menhir/tool_config.py
menhir/tool_utils.py
menhir/utils.py
menhir.egg-info/PKG-INFO
menhir.egg-info/SOURCES.txt
menhir.egg-info/dependency_links.txt
menhir.egg-info/entry_points.txt
menhir.egg-info/requires.txt
menhir.egg-info/top_level.txt
menhir/tools/__init__.py
menhir/tools/circleci.py
menhir/tools/codecov.py
menhir/tools/docker.py
menhir/tools/dynamodb.py
menhir/tools/ecs_deploy.py
menhir/tools/exec.py
menhir/tools/git.py
menhir/tools/git_status.py
menhir/tools/kms.py
menhir/tools/multiproject.py
menhir/tools/pprint.py
menhir/tools/pyenv.py
menhir/tools/pylama.py
menhir/tools/pytest.py
menhir/tools/setup_py.py
menhir/tools/terraform.py
menhir/tools/write_state.py
menhir/tools/codecov/upload.sh
menhir/tools/docker/docker-build.sh
menhir/tools/docker/docker-push.sh
menhir/tools/pyenv/requirements.sh
menhir/tools/pyenv/safety.sh
menhir/tools/pytest/test.sh
menhir/tools/setup_py/lambda-package.sh
menhir/tools/setup_py/wrapper.sh