Metadata-Version: 1.0
Name: menhir
Version: 0.0.80
Summary: A build tool for monolithic repositories
Home-page: https://github.com/dialoguemd/menhir
Author: Hugo Duncan
Author-email: hugo@hugoduncan.org
License: MIT
Platform: UNKNOWN
